Metadata-Version: 1.1
Name: video-frame-selector
Version: 0.0.9
Summary: Meta-tool that presents frames from a video to image analysis frameworks and uses the predictions to determine whether to use a frame or not.
Home-page: https://github.com/waikato-datamining/video-frame-processor
Author: Peter Reutemann
Author-email: fracpete@waikato.ac.nz
License: MIT License
Platform: UNKNOWN
Classifier: Development Status :: 4 - Beta
Classifier: License :: OSI Approved :: MIT License
Classifier: Topic :: Multimedia :: Video
Classifier: Programming Language :: Python :: 3
